coop_kobe_downloader/__init__.py
coop_kobe_downloader/__main__.py
coop_kobe_downloader/lib/__init__.py
coop_kobe_downloader/lib/driver.py
coop_kobe_downloader/lib/logger.py
coop_kobe_downloader/lib/week.py
coop_kobe_downloader-0.3.1.dist-info/METADATA
coop_kobe_downloader-0.3.1.dist-info/WHEEL
coop_kobe_downloader-0.3.1.dist-info/entry_points.txt
coop_kobe_downloader-0.3.1.dist-info/licenses/LICENSE
coop_kobe_downloader-0.3.1.dist-info/RECORD
