Metadata-Version: 2.3
Name: coop-kobe-downloader
Version: 0.3.1
Summary: Add your description here
Project-URL: Homepage, https://github.com/ryohidaka/coop-kobe-downloader
Project-URL: Repository, https://github.com/ryohidaka/coop-kobe-downloader
Project-URL: Issues, https://github.com/ryohidaka/coop-kobe-downloader/issues
Project-URL: Changelog, https://github.com/ryohidaka/blob/main/coop-kobe-downloader/CHANGELOG.md
Author-email: ryohidaka <39184410+ryohidaka@users.noreply.github.com>
License: MIT License
License-File: LICENSE
Keywords: coop,csv,japan,japanese,parser
Requires-Python: >=3.8
Requires-Dist: selenium>=4.22.0
Requires-Dist: webdriver-manager>=4.0.2
